[
    {
        "city": "Balneário Camboriú",
        "latitude": -26.994483,  
        "longitude": -48.634835,
        "address": "Rua 1950 , 634/casa - Centro" 
    },
    {
        "city": "Blumenau",
        "latitude": -26.893435, 
        "longitude": -49.083006,
        "address": "Rua São Paulo, 2963 - Itoupava Seca" 
    },
    {
        "city": "Brusque",
        "latitude": -27.084590, 
        "longitude": -48.912153,
        "address": "Rua: Otto Renaux, 500 sala 13, 500/sala 13 - centro" 
    },
    {
        "city": "Chapecó",
        "latitude": -27.107808, 
        "longitude": -52.619865,
        "address": "R. Clevelândia , 1389/D - SAIC" 
    },
    {
        "city": "Concórdia",
        "latitude": -27.230048, 
        "longitude": -52.025951,
        "address": "Rua Getúlio Vargas, 85/2º andar - Centro" 
    },
    {
        "city": "Criciúma",
        "latitude": -28.674334, 
        "longitude": -49.372800,
        "address": "Avenida Getúlio Vargas, 485/Ed. Bologna , Sala 41 - centro" 
    },
    {
        "city": "Florianópolis",
        "latitude": -27.612833, 
        "longitude": -48.525819,
        "address": "Rua Dep. Antonio Edu Vieira , 150/ - Pantanal" 
    },
    {
        "city": "Imbituba",
        "latitude": -28.240155, 
        "longitude": -48.669264,
        "address": "Avenida Santa Catarina, 819/ - Paes Leme" 
    },
    {
        "city": "Jaraguá do Sul",
        "latitude": -26.478897, 
        "longitude": -49.108806,
        "address": "Therezita Menegotti Rocha, 110/Casa - Água Verde" 
    },
    {
        "city": "Joaçaba",
        "latitude": -27.172333, 
        "longitude": -51.507798,
        "address": "Av. Barão do Rio Branco, 478/3º andar - Centro" 
    },
    {
        "city": "Joinville",
        "latitude": -26.267679, 
        "longitude": -48.836135,
        "address": "Rua Piratuba, 1.100/Prédio - Bom Retiro" 
    },
    {
        "city": "Lages",
        "latitude": -26.267684,  
        "longitude": -48.836136,
        "address": "R. José Ma. Antunes Ramos, 35 - Universitário" 
    },
    {
        "city": "Mafra",
        "latitude": -26.127476, 
        "longitude": -49.805775,
        "address": "Rua Siqueira Campos, 333/ - Alto de Mafra" 
    },
    {
        "city": "Rio do Sul",
        "latitude": -27.209136, 
        "longitude": -49.634796,
        "address": "Al. Bela Aliança, 1162/ - Jardim América" 
    },
    {
        "city": "São Bento do Sul",
        "latitude": -26.246098, 
        "longitude": -49.373233,
        "address": "Rua Doutor Cominese, 90/ - Centro" 
    },
    {
        "city": "Seara",
        "latitude": -27.147996, 
        "longitude": -52.309471,
        "address": "R. Vicente Rech , 230/Cx Postal 04 - Centro" 
    },
    {
        "city": "Timbó",
        "latitude": -26.831822, 
        "longitude": -49.265328,
        "address": "Rua Eduardo Frederico Mayr, 164 - Quintino" 
    },
    {
        "city": "Tubarão",
        "latitude": -28.479424, 
        "longitude": -49.013450,
        "address": "Rua Antonio Hulse, 541/ - Humaitá" 
    },
    {
        "city": "Videira",
        "latitude": -27.011091, 
        "longitude": -51.151056,
        "address": "Avenida Dom Pedro II, 47/apto 01 - Centro" 
    },
    {
        "city": "Bagé",
        "latitude": -31.313132,  
        "longitude": -54.093911,
        "address": "Rua Barão do Itaqui, 730/ - Getúlio Vargas" 
    },
    {
        "city": "Caxias do Sul",
        "latitude": -29.161749, 
        "longitude": -51.178196,
        "address": "Avenida São João, 1669/Casa - Centro" 
    },
    {
        "city": "Erechim",
        "latitude": -27.638038, 
        "longitude": -52.280728,
        "address": "Rua Salgado Filho, 737/ - Centro" 
    },
    {
        "city": "Passo Fundo",
        "latitude": -28.264062, 
        "longitude": -52.395692,
        "address": "Rua Coronel Pelegrini, 473/ - Vila Rodrigues" 
    },
    {
        "city": "Porto Alegre",
        "latitude": -30.028311, 
        "longitude": -51.203678,
        "address": "Rua Mostardeiro, 366/sala 501 - Moinhos de Vento" 
    },
    {
        "city": "Rio Grande",
        "latitude": -32.031584, 
        "longitude": -52.096354,
        "address": "Rua General Bacelar, 293/ - Centro" 
    },
    {
        "city": "São Leopoldo",
        "latitude": -29.768000, 
        "longitude": -51.132889,
        "address": "Rua São José, 617/ - São José" 
    },
    {
        "city": "Cascavel",
        "latitude": -24.961086, 
        "longitude": -53.467160,
        "address": "Rua Salgado Filho , 1577/ - Incra" 
    },
    {
        "city": "Curitiba",
        "latitude": -25.410301, 
        "longitude": -49.311719,
        "address": "Rua Angelo Domingos Durigan, 460/ - Santa Felicidade" 
    },
    {
        "city": "Foz do Iguaçu",
        "latitude": -25.535934, 
        "longitude": -54.554539,
        "address": "Av. Republica Argentina , 3830 /Sala 110 - Jardim Panorama" 
    },
    {
        "city": "Pato Branco",
        "latitude": -26.219242, 
        "longitude": -52.668918,
        "address": "Rua. Osvaldo Aranha, 906/ - CENTRO" 
    },
    {
        "city": "Ponta Grossa",
        "latitude": -25.082099, 
        "longitude": -50.165909,
        "address": "Rua Balduíno Taques, 2002/ - São José" 
    },
    {
        "city": "Águas de São Pedro",
        "latitude": -22.599440, 
        "longitude": -47.875761,
        "address": "Praça dos Rouxinois - Shopping Bellagio, s/n - S-10/S.Bellagio - Centro" 
    },
    {
        "city": "Bauru",
        "latitude": -22.327305, 
        "longitude": -49.060011,
        "address": "Rua Raposo Tavares, 9-41/-- - Jardim " 
    },
    {
        "city": "Campinas",
        "latitude": -22.879358,  
        "longitude": -47.060319,
        "address": "Rua Teofilo Braga, 327/ - Taquaral" 
    },
    {
        "city": "Franca",
        "latitude": -20.538855,  
        "longitude": -47.396974,
        "address": "Rua Marechal Deodoro, 1969/ - Centro" 
    },
    {
        "city": "Ribeirão Preto",
        "latitude": -21.195326, 
        "longitude": -47.817398,
        "address": "Rua Nélio Guimarães, 276/ - Alto da Boa Vista" 
    },
    {
        "city": "Santos",
        "latitude": -23.955371, 
        "longitude": -46.348266,
        "address": "Rua Benedito Ernesto Guimarães, 124/ - Marapé" 
    },
    {
        "city": "São José do Rio Pardo",
        "latitude": 0, 
        "longitude": 0,
        "address": "Rua Abdiel Cavalcanti Braga, 22/Térreo - Centro" 
    },
    {
        "city": "São José do Rio Preto",
        "latitude": -20.822505, 
        "longitude": -49.402691,
        "address": "AVENIDA DA LUZ, 821/Sala 3 - Alto Rio Preto" 
    },
    {
        "city": "São Paulo",
        "latitude": -23.576233, 
        "longitude": -46.645743,
        "address": "Rua Coronel Oscar Porto, 818/ - Paraíso" 
    },
    {
        "city": "São Paulo",
        "latitude": -23.617098, 
        "longitude": -46.629957,
        "address": "Rua General Chagas Santos, 590 - Saúde" 
    },
    {
        "city": "Taubaté",
        "latitude": -23.032453, 
        "longitude": -45.557824,
        "address": "Rua Antoninho Rocha Marmo, 30/ - Centro" 
    },
    {
        "city": "Cabo Frio",
        "latitude": -22.884205, 
        "longitude": -42.026742,
        "address": "Av. Teixeira e Souza , 928/loja 1 - Vila Nova" 
    },
    {
        "city": "Campo do Goytacazes",
        "latitude": -21.770302, 
        "longitude": -41.316494,
        "address": "Av. Vinte e Oito de Março (TURFECENTRO SHOPPING), 13/19 Lj34/LOJA 34 - TURF-CLUB" 
    },
    {
        "city": "Miguel Pereira",
        "latitude": 0, 
        "longitude": 0,
        "address": "Rua Carlos Delamare, 435/cj 5 - Centro" 
    },
    {
        "city": "Niterói",
        "latitude": -22.914653, 
        "longitude": -43.090924,
        "address": "Rua Tupinambás, 04/casa - São Francisco" 
    },
    {
        "city": "Nova Fraiburgo",
        "latitude": 0, 
        "longitude": 0,
        "address": "Rua Major Augusto Marques Braga, 18/sl. 203 - Centro" 
    },
    {
        "city": "Nova Iguaçu",
        "latitude": -22.760967, 
        "longitude": -43.451096,
        "address": "Rua Drº Paulo Fróes Machado, 58 Sl. 502/Sala 502 - Centro" 
    },
    {
        "city": "Petrópolis",
        "latitude": -22.503960, 
        "longitude": -43.190473,
        "address": "Av. Piabanha, 890/ - Centro" 
    },
    {
        "city": "Resende",
        "latitude": -22.463203, 
        "longitude": -44.445828,
        "address": "Rua Alan Kardec, 50/sala 310 - Jardim Tropical" 
    },
    {
        "city": "Rio de Janeiro",
        "latitude": -23.008112, 
        "longitude": -43.319174,
        "address": "R. John Kennedy, 461/ - Barra da Tijuca" 
    },
    {
        "city": "Rio de Janeiro",
        "latitude": -22.952591, 
        "longitude": -43.183327,
        "address": "Rua General Polidoro , 36/ - Botafogo" 
    },
    {
        "city": "Rio de Janeiro",
        "latitude": -22.901152,  
        "longitude": -43.180110,
        "address": "Av. Presidente Vargas, 446/Sala 1902 - Centro" 
    },
    {
        "city": "Rio de Janeiro",
        "latitude": -22.804465, 
        "longitude": -43.204377,
        "address": "Estrada do Galeão, 2315/203 - Ilha do Governador" 
    },
    {
        "city": "Rio de Janeiro",
        "latitude": -22.923428,  
        "longitude": -43.229161,
        "address": "Rua Conde de Bonfim, 232/sala 407 - Tijuca" 
    },
    {
        "city": "Teresópolis",
        "latitude": -22.413421, 
        "longitude": -42.967908,
        "address": "Av. Delfim Moreira, , 266/sala 405 - Várzea" 
    },
    {
        "city": "Três Rios",
        "latitude": -22.114909,  
        "longitude": -43.209378,
        "address": "Praça Martins Paixão, 05/101/101 - Centro" 
    },
    {
        "city": "",
        "latitude": 0, 
        "longitude": 0,
        "address": "" 
    },
    {
        "city": "",
        "latitude": 0, 
        "longitude": 0,
        "address": "" 
    },
    {
        "city": "",
        "latitude": 0, 
        "longitude": 0,
        "address": "" 
    },
    {
        "city": "",
        "latitude": 0, 
        "longitude": 0,
        "address": "" 
    },
    {
        "city": "",
        "latitude": 0, 
        "longitude": 0,
        "address": "" 
    }
    ,
    {
        "city": "",
        "latitude": 0, 
        "longitude": 0,
        "address": "" 
    }
]